AUTHORS
CHANGELOG.rst
LICENSE
MANIFEST.in
README.rst
pyproject.toml
setup.py
cyipopt/__init__.py
cyipopt/exceptions.py
cyipopt/ipopt_wrapper.py
cyipopt/scipy_interface.py
cyipopt/utils.py
cyipopt/version.py
cyipopt.egg-info/PKG-INFO
cyipopt.egg-info/SOURCES.txt
cyipopt.egg-info/dependency_links.txt
cyipopt.egg-info/not-zip-safe
cyipopt.egg-info/requires.txt
cyipopt.egg-info/top_level.txt
cyipopt/cython/ipopt.pxd
cyipopt/cython/ipopt_wrapper.pyx
cyipopt/tests/__init__.py
cyipopt/tests/conftest.py
cyipopt/tests/integration/__init__.py
cyipopt/tests/integration/test_hs071.py
cyipopt/tests/integration/test_lasso.py
cyipopt/tests/integration/test_rosen.py
cyipopt/tests/unit/__init__.py
cyipopt/tests/unit/test_defaults.py
cyipopt/tests/unit/test_deriv_errors.py
cyipopt/tests/unit/test_errors.py
cyipopt/tests/unit/test_exceptions.py
cyipopt/tests/unit/test_ipopt_funcs.py
cyipopt/tests/unit/test_options.py
cyipopt/tests/unit/test_scipy_optional.py
docs/Makefile
docs/make.bat
docs/requirements.txt
docs/source/conf.py
docs/source/development.rst
docs/source/index.rst
docs/source/install.rst
docs/source/reference.rst
docs/source/tutorial.rst
examples/exception_handling.py
examples/hs071.py
examples/hs071_scipy_jax.py
examples/lasso.py
examples/rosen.py