Metadata-Version: 2.4
Name: cyipopt
Version: 1.6.1
Summary: A Cython wrapper to the IPOPT optimization package
Home-page: https://github.com/mechmotum/cyipopt
Author: Jason K. Moore
Author-email: moorepants@gmail.com
License: EPL-2.0
Keywords: coin-or,interior-point,ipopt,nlp,nonlinear programming,optimization
Classifier: Development Status :: 5 - Production/Stable
Classifier: License :: OSI Approved :: Eclipse Public License 2.0 (EPL-2.0)
Classifier: Intended Audience :: Science/Research
Classifier: Operating System :: OS Independent
Classifier: Programming Language :: Python :: 3.9
Classifier: Programming Language :: Python :: 3.10
Classifier: Programming Language :: Python :: 3.11
Classifier: Programming Language :: Python :: 3.12
Classifier: Programming Language :: Python :: 3.13
License-File: LICENSE
License-File: AUTHORS
Requires-Dist: numpy>=1.26.4
Dynamic: author
Dynamic: author-email
Dynamic: classifier
Dynamic: description
Dynamic: home-page
Dynamic: keywords
Dynamic: license
Dynamic: license-file
Dynamic: requires-dist
Dynamic: summary
